manuskript
rekall_gui
