Metadata-Version: 1.1
Name: rekall-gui
Version: 1.4.1
Summary: Rekall Memory Forensic Framework
Home-page: https://www.rekall-forensic.com/
Author: The Rekall team
Author-email: rekall-discuss@googlegroups.com
License: GPL
Platform: UNKNOWN
Classifier: Development Status :: 4 - Beta
Classifier: Environment :: Console
Classifier: Operating System :: OS Independent
Classifier: Programming Language :: Python
